deepkeep/__init__.py
deepkeep/__main__.py
deepkeep/_client.py
deepkeep/_exceptions.py
deepkeep/modules/__init__.py
deepkeep/modules/applications/__init__.py
deepkeep/modules/applications/applications.py
deepkeep/modules/base_module.py
deepkeep/modules/chat/__init__.py
deepkeep/modules/chat/chat.py
deepkeep/modules/chat/conversation.py
deepkeep/modules/chat/message.py
deepkeep/modules/evaluation/__init__.py
deepkeep/modules/evaluation/evaluation.py
deepkeep/modules/evaluation/report.py
deepkeep/modules/evaluation/topic.py
deepkeep/modules/evaluation/topic_option.py
deepkeep/modules/firewall/__init__.py
deepkeep/modules/firewall/filter.py
deepkeep/modules/firewall/firewall.py
deepkeep/modules/firewall/templates.py
deepkeep/modules/integrations/__init__.py
deepkeep/modules/integrations/consts.py
deepkeep/modules/integrations/integrations.py
deepkeep/modules/integrations/integrations_sources/__init__.py
deepkeep/modules/integrations/integrations_sources/azure_openai.py
deepkeep/modules/integrations/integrations_sources/bedrock.py
deepkeep/modules/integrations/integrations_sources/gemini.py
deepkeep/modules/integrations/integrations_sources/openai.py
deepkeep/modules/model/__init__.py
deepkeep/modules/model/integration_models/__init__.py
deepkeep/modules/model/integration_models/azure_openai.py
deepkeep/modules/model/integration_models/bedrock.py
deepkeep/modules/model/integration_models/gemini.py
deepkeep/modules/model/integration_models/openai.py
deepkeep/modules/model/model.py
deepkeep/modules/model/utils.py
deepkeep/modules/pipeline/__init__.py
deepkeep/modules/pipeline/pipeline.py
deepkeep/modules/report/__init__.py
deepkeep/modules/report/report.py
deepkeep-1.2.13.dist-info/LICENSE
deepkeep-1.2.13.dist-info/METADATA
deepkeep-1.2.13.dist-info/WHEEL
deepkeep-1.2.13.dist-info/RECORD
