Metadata-Version: 2.1
Name: deepkeep
Version: 1.2.13
Summary: The official Python library for the Deepkeep API
License: Apache-2.0
Author: DeepKeep Devs
Author-email: dev@deepkeep.ai
Requires-Python: >=3.10,<3.11
Classifier: Intended Audience :: Developers
Classifier: License :: OSI Approved :: Apache Software License
Classifier: Operating System :: MacOS
Classifier: Operating System :: Microsoft :: Windows
Classifier: Operating System :: OS Independent
Classifier: Operating System :: POSIX
Classifier: Operating System :: POSIX :: Linux
Classifier: Programming Language :: Python :: 3
Classifier: Programming Language :: Python :: 3.10
Classifier: Programming Language :: Python :: 3.11
Classifier: Programming Language :: Python :: 3.12
Classifier: Programming Language :: Python :: 3.7
Classifier: Programming Language :: Python :: 3.8
Classifier: Programming Language :: Python :: 3.9
Classifier: Topic :: Software Development :: Libraries :: Python Modules
Classifier: Typing :: Typed
Requires-Dist: anyio (>=4.3.0,<5.0.0)
Requires-Dist: distro (>=1.9.0,<2.0.0)
Requires-Dist: httpx (>=0.27.0,<0.28.0)
Requires-Dist: lock (>=2018.3.25.2110,<2019.0.0.0)
Requires-Dist: pydantic (>=2.6.3,<3.0.0)
Requires-Dist: requests (>=2.22.0,<3.0.0)
Requires-Dist: sniffio (>=1.3.1,<2.0.0)
Requires-Dist: tqdm (>=4.66.2,<5.0.0)
Requires-Dist: typing-extensions (>=4.10.0,<5.0.0)
Requires-Dist: update (>=0.0.1,<0.0.2)
